arcane/dataflow/__init__.py
arcane/dataflow/dataflow.py
arcane_dataflow-0.1.0.dist-info/WHEEL
arcane_dataflow-0.1.0.dist-info/METADATA
arcane_dataflow-0.1.0.dist-info/RECORD
