Metadata-Version: 2.1
Name: arcane-dataflow
Version: 0.1.0
Summary: Helpers for google dataflow services
Author: Arcane
Author-email: product@arcane.run
Requires-Python: >=3.6,<4.0
Classifier: Programming Language :: Python :: 3
Classifier: Programming Language :: Python :: 3.6
Classifier: Programming Language :: Python :: 3.7
Classifier: Programming Language :: Python :: 3.8
Classifier: Programming Language :: Python :: 3.9
Requires-Dist: google-api-python-client (==1.7.8)
Requires-Dist: oauth2client (==4.1.3)
